Workbook

Sheet サマリ
B1: 売価計算結果
B3: ・月間集計(汁の売上を除く)
D4: 食数 | H4: 売上 | L4: 1食あたりの平均売価(配送料込み) | P4: 1食あたりの平均売価(配送料除く)
D5: 朝食 | E5: 昼食 | F5: 夕食 | G5: 合計 | H5: 朝食 | I5: 昼食 | J5: 夕食 | K5: 合計 | L5: 朝食 | M5: 昼食 | N5: 夕食 | O5: 合計 | P5: 朝食 | Q5: 昼食 | R5: 夕食 | S5: 合計
B6: 常食・薄味・個食・フリーズのみ | D6: =食事区分毎詳細!C16 -> 0 | E6: =食事区分毎詳細!D16 -> 0 | F6: =食事区分毎詳細!E16 -> 0 | G6: =SUM(D6:F6) -> 0 | H6: =食事区分毎詳細!G16 -> 0 | I6: =食事区分毎詳細!H16 -> 0 | J6: =食事区分毎詳細!I16 -> 0 | K6: =SUM(H6:J6) -> 0 | L6: =H6/D6 -> #DIV/0! | M6: =I6/E6 -> #DIV/0! | N6: =J6/F6 -> #DIV/0! | O6: =SUM(L6:N6) -> #DIV/0! | P6: =L6-H20 -> #DIV/0! | Q6: =M6-I20 -> #DIV/0! | R6: =N6-J20 -> #DIV/0! | S6: =SUM(P6:R6) -> #DIV/0!
B7: 嚥下 | D7: =食事区分毎詳細!C15 -> 0 | E7: =食事区分毎詳細!D15 -> 0 | F7: =食事区分毎詳細!E15 -> 0 | G7: =SUM(D7:F7) -> 0 | H7: =食事区分毎詳細!G15 -> 0 | I7: =食事区分毎詳細!H15 -> 0 | J7: =食事区分毎詳細!I15 -> 0 | K7: =SUM(H7:J7) -> 0 | L7: =H7/D7 -> #DIV/0! | M7: =I7/E7 -> #DIV/0! | N7: =J7/F7 -> #DIV/0! | O7: =SUM(L7:N7) -> #DIV/0! | P7: =L7-H20 -> #DIV/0! | Q7: =M7-I20 -> #DIV/0! | R7: =N7-J20 -> #DIV/0! | S7: =SUM(P7:R7) -> #DIV/0!
B8: 全体 | D8: =SUM(D6:D7) -> 0 | E8: =SUM(E6:E7) -> 0 | F8: =SUM(F6:F7) -> 0 | G8: =SUM(G6:G7) -> 0 | H8: =SUM(H6:H7) -> 0 | I8: =SUM(I6:I7) -> 0 | J8: =SUM(J6:J7) -> 0 | K8: =SUM(K6:K7) -> 0 | L8: =H6/D8+H7/D8 -> #DIV/0! | M8: =I6/E8+I7/E8 -> #DIV/0! | N8: =J6/F8+J7/F8 -> #DIV/0! | O8: =SUM(L8:N8) -> #DIV/0! | P8: =L8-H20 -> #DIV/0! | Q8: =M8-I20 -> #DIV/0! | R8: =N8-J20 -> #DIV/0! | S8: =SUM(P8:R8) -> #DIV/0!
B10: ・月間集計(汁の売上を含む)
D11: 食数 | H11: 売上 | L11: 1食あたりの平均売価(配送料込み) | P11: 1食あたりの平均売価(配送料除く)
D12: 朝食 | E12: 昼食 | F12: 夕食 | G12: 合計 | H12: 朝食 | I12: 昼食 | J12: 夕食 | K12: 合計 | L12: 朝食 | M12: 昼食 | N12: 夕食 | O12: 合計 | P12: 朝食 | Q12: 昼食 | R12: 夕食 | S12: 合計
B13: 常食・薄味・個食・フリーズのみ | D13: =D6 -> 0 | E13: =E6 -> 0 | F13: =F6 -> 0 | G13: =SUM(D13:F13) -> 0 | H13: =食事区分毎詳細!K16 -> 0 | I13: =食事区分毎詳細!L16 -> 0 | J13: =食事区分毎詳細!M16 -> 0 | K13: =SUM(H13:J13) -> 0 | L13: =H13/D13 -> #DIV/0! | M13: =I13/E13 -> #DIV/0! | N13: =J13/F13 -> #DIV/0! | O13: =SUM(L13:N13) -> #DIV/0! | P13: =L13-H20 -> #DIV/0! | Q13: =M13-I20 -> #DIV/0! | R13: =N13-J20 -> #DIV/0! | S13: =SUM(P13:R13) -> #DIV/0!
B14: 嚥下 | D14: =D7 -> 0 | E14: =E7 -> 0 | F14: =F7 -> 0 | G14: =SUM(D14:F14) -> 0 | H14: =食事区分毎詳細!K15 -> 0 | I14: =食事区分毎詳細!L15 -> 0 | J14: =食事区分毎詳細!M15 -> 0 | K14: =SUM(H14:J14) -> 0 | L14: =H14/D14 -> #DIV/0! | M14: =I14/E14 -> #DIV/0! | N14: =J14/F14 -> #DIV/0! | O14: =SUM(L14:N14) -> #DIV/0! | P14: =L14-H20 -> #DIV/0! | Q14: =M14-I20 -> #DIV/0! | R14: =N14-J20 -> #DIV/0! | S14: =SUM(P14:R14) -> #DIV/0!
B15: 全体 | D15: =SUM(D13:D14) -> 0 | E15: =SUM(E13:E14) -> 0 | F15: =SUM(F13:F14) -> 0 | G15: =SUM(G13:G14) -> 0 | H15: =SUM(H13:H14) -> 0 | I15: =SUM(I13:I14) -> 0 | J15: =SUM(J13:J14) -> 0 | K15: =SUM(K13:K14) -> 0 | L15: =H13/D15+H14/D15 -> #DIV/0! | M15: =I13/E15+I14/E15 -> #DIV/0! | N15: =J13/F15+J14/F15 -> #DIV/0! | O15: =SUM(L15:N15) -> #DIV/0! | P15: =L15-H20 -> #DIV/0! | Q15: =M15-I20 -> #DIV/0! | R15: =N15-J20 -> #DIV/0! | S15: =SUM(P15:R15) -> #DIV/0!
B17: ・配送料
B18: 今月の配送料の請求金額 | D18: 1日あたりの平均配送料 | H18: 食事区分別配送料
D19: =B19/食事区分毎詳細!F5*3 -> #DIV/0! | H19: 朝食 | I19: 昼食 | J19: 夕食 | K19: 合計
H20: =$D$19/SUM(参照!$G$6:$I$6)*参照!G6 -> #DIV/0! | I20: =$D$19/SUM(参照!$G$6:$I$6)*参照!H6 -> #DIV/0! | J20: =$D$19/SUM(参照!$G$6:$I$6)*参照!I6 -> #DIV/0! | K20: =SUM(H20:J20) -> #DIV/0!
B22: ・1ヶ月の1日あたりの単純平均売価(汁の売上を除く) | H22: ・1ヶ月の1日あたりの単純平均売価(汁の売上を含む)
B23: ・常食・薄味・個食・フリーズのみ | H23: ・常食・薄味・個食・フリーズのみ
B24: 配送料込み | D24: =K6/G6*3 -> #DIV/0! | H24: 配送料込み | J24: =K13/G13*3 -> #DIV/0!
B25: 配送料除く | D25: =D24-$D$19 -> #DIV/0! | H25: 配送料除く | J25: =J24-$D$19 -> #DIV/0!
B27: ・嚥下 | H27: ・嚥下
B28: 配送料込み | D28: =K7/G7*3 -> #DIV/0! | H28: 配送料込み | J28: =K14/G14*3 -> #DIV/0!
B29: 配送料除く | D29: =D28-$D$19 -> #DIV/0! | H29: 配送料除く | J29: =J28-$D$19 -> #DIV/0!
B31: ・全体 | H31: ・全体
B32: 配送料込み | D32: =K8/G8*3 -> #DIV/0! | H32: 配送料込み | J32: =K15/G15*3 -> #DIV/0!
B33: 配送料除く | D33: =D32-$D$19 -> #DIV/0! | H33: 配送料除く | J33: =J32-$D$19 -> #DIV/0!

Sheet 食事区分毎詳細
B1: 食事区分毎集計結果詳細(1ヶ月分)
B2: ※下記売上は配送料を含む
C3: 食数 | G3: 売上(汁の売上を除く) | K3: 売上(汁の売上を含む)
C4: 朝食 | D4: 昼食 | E4: 夕食 | F4: 合計 | G4: 朝食 | H4: 昼食 | I4: 夕食 | J4: 合計 | K4: 朝食 | L4: 昼食 | M4: 夕食 | N4: 合計
B5: 全体 | F5: =SUM(C5:E5) -> 0 | G5: =K5-SUM(G6:G7) -> 0 | H5: =L5-SUM(H6:H7) -> 0 | I5: =M5-SUM(I6:I7) -> 0 | J5: =SUM(G5:I5) -> 0 | N5: =SUM(K5:M5) -> 0
B6: 具のみ | F6: =SUM(C6:E6) -> 0 | G6: =C6*参照!C7 -> 0 | H6: =D6*参照!D7 -> 0 | I6: =E6*参照!E7 -> 0 | J6: =SUM(G6:I6) -> 0 | K6: =G6 -> 0 | L6: =H6 -> 0 | M6: =I6 -> 0 | N6: =SUM(K6:M6) -> 0
B7: 汁具のみ | F7: =SUM(C7:E7) -> 0 | G7: =C7*参照!C6 -> 0 | H7: =D7*参照!D6 -> 0 | I7: =E7*参照!E6 -> 0 | J7: =SUM(G7:I7) -> 0 | K7: =G7 -> 0 | L7: =H7 -> 0 | M7: =I7 -> 0 | N7: =SUM(K7:M7) -> 0
B8: 具のみ(嚥下以外) | F8: =SUM(C8:E8) -> 0 | G8: =C8*参照!C7 -> 0 | H8: =D8*参照!D7 -> 0 | I8: =E8*参照!E7 -> 0 | J8: =SUM(G8:I8) -> 0 | K8: =G8 -> 0 | L8: =H8 -> 0 | M8: =I8 -> 0 | N8: =SUM(K8:M8) -> 0
B9: 具のみ(嚥下) | F9: =SUM(C9:E9) -> 0 | G9: =C9*参照!C7 -> 0 | H9: =D9*参照!D7 -> 0 | I9: =E9*参照!E7 -> 0 | J9: =SUM(G9:I9) -> 0 | K9: =G9 -> 0 | L9: =H9 -> 0 | M9: =I9 -> 0 | N9: =SUM(K9:M9) -> 0
B10: 汁具のみ(嚥下以外) | F10: =SUM(C10:E10) -> 0 | G10: =C10*参照!C6 -> 0 | H10: =D10*参照!D6 -> 0 | I10: =E10*参照!E6 -> 0 | J10: =SUM(G10:I10) -> 0 | K10: =G10 -> 0 | L10: =H10 -> 0 | M10: =I10 -> 0 | N10: =SUM(K10:M10) -> 0
B11: 汁具のみ(嚥下) | F11: =SUM(C11:E11) -> 0 | G11: =C11*参照!C6 -> 0 | H11: =D11*参照!D6 -> 0 | I11: =E11*参照!E6 -> 0 | J11: =SUM(G11:I11) -> 0 | K11: =G11 -> 0 | L11: =H11 -> 0 | M11: =I11 -> 0 | N11: =SUM(K11:M11) -> 0
B12: 嚥下(ソフト) | F12: =SUM(C12:E12) -> 0 | J12: =SUM(G12:I12) -> 0 | N12: =SUM(K12:M12) -> 0
B13: 嚥下(ミキサー) | F13: =SUM(C13:E13) -> 0 | J13: =SUM(G13:I13) -> 0 | N13: =SUM(K13:M13) -> 0
B14: 嚥下(ゼリー) | F14: =SUM(C14:E14) -> 0 | J14: =SUM(G14:I14) -> 0 | N14: =SUM(K14:M14) -> 0
B15: 嚥下(合計) | C15: =SUM(C12:C14) -> 0 | D15: =SUM(D12:D14) -> 0 | E15: =SUM(E12:E14) -> 0 | F15: =SUM(C15:E15) -> 0 | G15: =SUM(G12:G14) -> 0 | H15: =SUM(H12:H14) -> 0 | I15: =SUM(I12:I14) -> 0 | J15: =SUM(G15:I15) -> 0 | K15: =SUM(K12:K14) -> 0 | L15: =SUM(L12:L14) -> 0 | M15: =SUM(M12:M14) -> 0 | N15: =SUM(K15:M15) -> 0
B16: 常食・薄味・個食・フリーズのみ | C16: =C5-C15 -> 0 | D16: =D5-D15 -> 0 | E16: =E5-E15 -> 0 | F16: =SUM(C16:E16) -> 0 | G16: =G5-G17-G18 -> 0 | H16: =H5-H17-H18 -> 0 | I16: =I5-I17-I18 -> 0 | J16: =SUM(G16:I16) -> 0 | K16: =K5-K17-K18 -> 0 | L16: =L5-L17-L18 -> 0 | M16: =M5-M17-M18 -> 0 | N16: =SUM(K16:M16) -> 0
B17: -売価が別の施設の嚥下(売価) | F17: =SUM(C17:E17) -> 0 | J17: =SUM(G17:I17) -> 0 | N17: =SUM(K17:M17) -> 0
B18: -売価が同じ施設の嚥下(売価) | F18: =SUM(C18:E18) -> 0 | J18: =SUM(G18:I18) -> 0 | N18: =SUM(K18:M18) -> 0

Sheet 施設毎詳細
B2: 施設・食事区分単位集計
B3: 施設名 | C3: 食事区分 | D3: 汁内容 | E3: 種別 | F3: 通常単価 | G3: 嚥下単価 | H3: 単価が別かどうか | I3: 嚥下以外の常食・薄味・個食・フリーズ食数 | J3: 嚥下食数 | K3: 食数総合計 | L3: 嚥下以外の常食・薄味・個食・フリーズ売上 | M3: 嚥下食売上 | N3: 売上総合計

Sheet 参照
B2: 参照テーブル
B4: オプション価格 | G4: 配送料割合
B5: オプション内容 | C5: 朝 | D5: 昼 | E5: 夕 | G5: 朝 | H5: 昼 | I5: 夕
B6: 汁具 | C6: 40 | D6: 40 | E6: 40 | G6: 1 | H6: 2 | I6: 2
B7: 具のみ | C7: 30 | D7: 30 | E7: 30

Sheet (参考)売価計算仕様
B2: [サマリ仕様]
B3: 1ヶ月分の朝昼夕別の売上ー1ヶ月分の朝昼夕別の具のみ（30円/回）の売上
B4: ー1ヶ月分の朝昼夕別の汁具（40円/回）の売上ー1ヶ月分の朝昼夕別の嚥下食の売上（売価が別になっている施設分）
B5: ー1ヶ月分の朝昼夕別の嚥下食の売上（売価が別になっていない施設分は売価で計算）＝1ヶ月分の朝昼夕別の常食・薄味・個食・フリーズのみの売上（運賃込み）・・・①
B7: 1ヶ月分の朝昼夕別の食数ー1ヶ月分の朝昼夕別の嚥下食の食数＝1ヶ月分の朝昼夕別の常食・薄味・個食・フリーズのみの合計食数・・・②
B9: ①÷②＝1ヶ月分の朝昼夕別の常食・薄味・個食・フリーズのみの平均売価とその合計
B11: 運賃計算については下記の通りです。
B12: 佐川急便などの運賃の請求合計額（税別）÷1ヶ月分の朝昼夕の合計食数＝1食当たりの平均運賃を算出・・・③
B13: ③ x 3（朝昼夕）＝平均運賃/セット食（朝昼夕）/日・・・④
B14: 弊社の社内での運賃割合を下記の通り設定
B15: 朝=１: 昼=２: 夕=２
B16: 上記の平均運賃/セット食（朝昼夕）/日と弊社の社内での運賃割合で朝・昼・夕別の運賃を算出・・・⑤
... B33: 1ヶ月分の朝昼夕別の嚥下食の平均売価とその合計
B35: 1ヶ月分の朝昼夕別の常食・薄味・個食・フリーズのみの売上・・・①とその合計 | J35: ※汁のオプション料金は除いた売上
B36: 1ヶ月分の朝昼夕別の常食・薄味・個食・フリーズのみの合計食数・・・②とその合計
B37: 1ヶ月分の朝昼夕別の常食・薄味・個食・フリーズのみの平均売価とその合計
B38: 1ヶ月分の常食・薄味・個食・フリーズのみの売上÷1ヶ月分の常食・薄味・個食・フリーズのみの合計食数ｘ3（朝昼夕）＝1日の常食・薄味・個食・フリーズのみの平均売価
B39: ※上記はすべて運賃込みの売価
B41: 上記の運賃計算で算出した④と⑤を利用して上記の各平均売価より差引いて運賃を除く平均売価を算出お願い致します。
B42: 1ヶ月分の朝昼夕別の平均売価とその合計（運賃除く）
B43: 1ヶ月分の朝昼夕別の嚥下食の平均売価とその合計（運賃除く）
B44: 1ヶ月分の朝昼夕別の常食・薄味・個食・フリーズのみの平均売価とその合計（運賃除く）
B45: 1ヶ月分の常食・薄味・個食・フリーズのみの売上÷1ヶ月分の常食・薄味・個食・フリーズのみの合計食数ｘ3（朝昼夕）＝1日の常食・薄味・個食・フリーズのみの平均売価（運賃除く）
